{
  "id": "21be6730-0eb5-408c-8b95-1668f04e3c14",
  "prevId": "ffaacb61-9ea1-44f8-90e2-a60258f8fd67",
  "version": "5",
  "dialect": "pg",
  "tables": {
    "accounts": {
      "name": "accounts",
      "schema": "",
      "columns": {
        "userId": {
          "name": "userId",
          "type": "text",
          "primaryKey": false,
          "notNull": true
        },
        "type": {
          "name": "type",
          "type": "text",
          "primaryKey": false,
          "notNull": true
        },
        "provider": {
          "name": "provider",
          "type": "text",
          "primaryKey": false,
          "notNull": true
        },
        "providerAccountId": {
          "name": "providerAccountId",
          "type": "text",
          "primaryKey": false,
          "notNull": true
        },
        "refresh_token": {
          "name": "refresh_token",
          "type": "text",
          "primaryKey": false,
          "notNull": false
        },
        "access_token": {
          "name": "access_token",
          "type": "text",
          "primaryKey": false,
          "notNull": false
        },
        "expires_at": {
          "name": "expires_at",
          "type": "integer",
          "primaryKey": false,
          "notNull": false
        },
        "token_type": {
          "name": "token_type",
          "type": "text",
          "primaryKey": false,
          "notNull": false
        },
        "scope": {
          "name": "scope",
          "type": "text",
          "primaryKey": false,
          "notNull": false
        },
        "id_token": {
          "name": "id_token",
          "type": "text",
          "primaryKey": false,
          "notNull": false
        },
        "session_state": {
          "name": "session_state",
          "type": "text",
          "primaryKey": false,
          "notNull": false
        },
        "createdAt": {
          "name": "createdAt",
          "type": "timestamp",
          "primaryKey": false,
          "notNull": false,
          "default": "now()"
        }
      },
      "indexes": {},
      "foreignKeys": {
        "accounts_userId_users_id_fk": {
          "name": "accounts_userId_users_id_fk",
          "tableFrom": "accounts",
          "tableTo": "users",
          "columnsFrom": [
            "userId"
          ],
          "columnsTo": [
            "id"
          ],
          "onDelete": "cascade",
          "onUpdate": "no action"
        }
      },
      "compositePrimaryKeys": {
        "accounts_provider_providerAccountId_pk": {
          "name": "accounts_provider_providerAccountId_pk",
          "columns": [
            "provider",
            "providerAccountId"
          ]
        }
      },
      "uniqueConstraints": {}
    },
    "authors": {
      "name": "authors",
      "schema": "",
      "columns": {
        "id": {
          "name": "id",
          "type": "serial",
          "primaryKey": true,
          "notNull": true
        },
        "name": {
          "name": "name",
          "type": "text",
          "primaryKey": false,
          "notNull": true
        }
      },
      "indexes": {},
      "foreignKeys": {},
      "compositePrimaryKeys": {},
      "uniqueConstraints": {}
    },
    "examples": {
      "name": "examples",
      "schema": "",
      "columns": {
        "id": {
          "name": "id",
          "type": "serial",
          "primaryKey": true,
          "notNull": true
        },
        "sentence": {
          "name": "sentence",
          "type": "text",
          "primaryKey": false,
          "notNull": true
        },
        "author_id": {
          "name": "author_id",
          "type": "integer",
          "primaryKey": false,
          "notNull": false
        }
      },
      "indexes": {},
      "foreignKeys": {
        "examples_author_id_authors_id_fk": {
          "name": "examples_author_id_authors_id_fk",
          "tableFrom": "examples",
          "tableTo": "authors",
          "columnsFrom": [
            "author_id"
          ],
          "columnsTo": [
            "id"
          ],
          "onDelete": "cascade",
          "onUpdate": "no action"
        }
      },
      "compositePrimaryKeys": {},
      "uniqueConstraints": {}
    },
    "meaning_attributes": {
      "name": "meaning_attributes",
      "schema": "",
      "columns": {
        "id": {
          "name": "id",
          "type": "serial",
          "primaryKey": true,
          "notNull": true
        },
        "attribute": {
          "name": "attribute",
          "type": "varchar(255)",
          "primaryKey": false,
          "notNull": true
        }
      },
      "indexes": {},
      "foreignKeys": {},
      "compositePrimaryKeys": {},
      "uniqueConstraints": {}
    },
    "meanings_attributes": {
      "name": "meanings_attributes",
      "schema": "",
      "columns": {
        "meaning_id": {
          "name": "meaning_id",
          "type": "serial",
          "primaryKey": false,
          "notNull": true
        },
        "attribute_id": {
          "name": "attribute_id",
          "type": "serial",
          "primaryKey": false,
          "notNull": true
        }
      },
      "indexes": {},
      "foreignKeys": {
        "meanings_attributes_meaning_id_meanings_id_fk": {
          "name": "meanings_attributes_meaning_id_meanings_id_fk",
          "tableFrom": "meanings_attributes",
          "tableTo": "meanings",
          "columnsFrom": [
            "meaning_id"
          ],
          "columnsTo": [
            "id"
          ],
          "onDelete": "cascade",
          "onUpdate": "no action"
        },
        "meanings_attributes_attribute_id_meaning_attributes_id_fk": {
          "name": "meanings_attributes_attribute_id_meaning_attributes_id_fk",
          "tableFrom": "meanings_attributes",
          "tableTo": "meaning_attributes",
          "columnsFrom": [
            "attribute_id"
          ],
          "columnsTo": [
            "id"
          ],
          "onDelete": "cascade",
          "onUpdate": "no action"
        }
      },
      "compositePrimaryKeys": {
        "meanings_attributes_meaning_id_attribute_id_pk": {
          "name": "meanings_attributes_meaning_id_attribute_id_pk",
          "columns": [
            "meaning_id",
            "attribute_id"
          ]
        }
      },
      "uniqueConstraints": {}
    },
    "meanings": {
      "name": "meanings",
      "schema": "",
      "columns": {
        "id": {
          "name": "id",
          "type": "serial",
          "primaryKey": true,
          "notNull": true
        },
        "meaning": {
          "name": "meaning",
          "type": "text",
          "primaryKey": false,
          "notNull": true
        },
        "word_id": {
          "name": "word_id",
          "type": "integer",
          "primaryKey": false,
          "notNull": true
        },
        "imageUrl": {
          "name": "imageUrl",
          "type": "varchar(255)",
          "primaryKey": false,
          "notNull": false
        },
        "part_of_speech_id": {
          "name": "part_of_speech_id",
          "type": "integer",
          "primaryKey": false,
          "notNull": true
        }
      },
      "indexes": {},
      "foreignKeys": {
        "meanings_word_id_words_id_fk": {
          "name": "meanings_word_id_words_id_fk",
          "tableFrom": "meanings",
          "tableTo": "words",
          "columnsFrom": [
            "word_id"
          ],
          "columnsTo": [
            "id"
          ],
          "onDelete": "cascade",
          "onUpdate": "no action"
        },
        "meanings_part_of_speech_id_part_of_speechs_id_fk": {
          "name": "meanings_part_of_speech_id_part_of_speechs_id_fk",
          "tableFrom": "meanings",
          "tableTo": "part_of_speechs",
          "columnsFrom": [
            "part_of_speech_id"
          ],
          "columnsTo": [
            "id"
          ],
          "onDelete": "no action",
          "onUpdate": "no action"
        }
      },
      "compositePrimaryKeys": {},
      "uniqueConstraints": {}
    },
    "part_of_speechs": {
      "name": "part_of_speechs",
      "schema": "",
      "columns": {
        "id": {
          "name": "id",
          "type": "serial",
          "primaryKey": true,
          "notNull": true
        },
        "partOfSpeech": {
          "name": "partOfSpeech",
          "type": "partOfSpeech",
          "primaryKey": false,
          "notNull": true
        }
      },
      "indexes": {},
      "foreignKeys": {},
      "compositePrimaryKeys": {},
      "uniqueConstraints": {}
    },
    "pronounciations": {
      "name": "pronounciations",
      "schema": "",
      "columns": {
        "id": {
          "name": "id",
          "type": "serial",
          "primaryKey": true,
          "notNull": true
        },
        "word_id": {
          "name": "word_id",
          "type": "integer",
          "primaryKey": false,
          "notNull": true
        },
        "user_id": {
          "name": "user_id",
          "type": "text",
          "primaryKey": false,
          "notNull": true
        },
        "audio_url": {
          "name": "audio_url",
          "type": "varchar(255)",
          "primaryKey": false,
          "notNull": true
        }
      },
      "indexes": {},
      "foreignKeys": {
        "pronounciations_word_id_words_id_fk": {
          "name": "pronounciations_word_id_words_id_fk",
          "tableFrom": "pronounciations",
          "tableTo": "words",
          "columnsFrom": [
            "word_id"
          ],
          "columnsTo": [
            "id"
          ],
          "onDelete": "cascade",
          "onUpdate": "no action"
        },
        "pronounciations_user_id_users_id_fk": {
          "name": "pronounciations_user_id_users_id_fk",
          "tableFrom": "pronounciations",
          "tableTo": "users",
          "columnsFrom": [
            "user_id"
          ],
          "columnsTo": [
            "id"
          ],
          "onDelete": "cascade",
          "onUpdate": "no action"
        }
      },
      "compositePrimaryKeys": {},
      "uniqueConstraints": {}
    },
    "related_words": {
      "name": "related_words",
      "schema": "",
      "columns": {
        "word_id": {
          "name": "word_id",
          "type": "integer",
          "primaryKey": false,
          "notNull": true
        },
        "related_word_id": {
          "name": "related_word_id",
          "type": "integer",
          "primaryKey": false,
          "notNull": true
        }
      },
      "indexes": {},
      "foreignKeys": {
        "related_words_word_id_words_id_fk": {
          "name": "related_words_word_id_words_id_fk",
          "tableFrom": "related_words",
          "tableTo": "words",
          "columnsFrom": [
            "word_id"
          ],
          "columnsTo": [
            "id"
          ],
          "onDelete": "cascade",
          "onUpdate": "no action"
        },
        "related_words_related_word_id_words_id_fk": {
          "name": "related_words_related_word_id_words_id_fk",
          "tableFrom": "related_words",
          "tableTo": "words",
          "columnsFrom": [
            "related_word_id"
          ],
          "columnsTo": [
            "id"
          ],
          "onDelete": "cascade",
          "onUpdate": "no action"
        }
      },
      "compositePrimaryKeys": {},
      "uniqueConstraints": {}
    },
    "requests": {
      "name": "requests",
      "schema": "",
      "columns": {
        "id": {
          "name": "id",
          "type": "serial",
          "primaryKey": true,
          "notNull": true
        },
        "user_id": {
          "name": "user_id",
          "type": "text",
          "primaryKey": false,
          "notNull": true
        },
        "entity_type": {
          "name": "entity_type",
          "type": "entity_type",
          "primaryKey": false,
          "notNull": true
        },
        "entity_id": {
          "name": "entity_id",
          "type": "integer",
          "primaryKey": false,
          "notNull": false
        },
        "action": {
          "name": "action",
          "type": "action",
          "primaryKey": false,
          "notNull": true
        },
        "new_data": {
          "name": "new_data",
          "type": "jsonb",
          "primaryKey": false,
          "notNull": false
        },
        "request_date": {
          "name": "request_date",
          "type": "timestamp",
          "primaryKey": false,
          "notNull": false,
          "default": "now()"
        },
        "status": {
          "name": "status",
          "type": "status",
          "primaryKey": false,
          "notNull": false,
          "default": "'pending'"
        }
      },
      "indexes": {},
      "foreignKeys": {
        "requests_user_id_users_id_fk": {
          "name": "requests_user_id_users_id_fk",
          "tableFrom": "requests",
          "tableTo": "users",
          "columnsFrom": [
            "user_id"
          ],
          "columnsTo": [
            "id"
          ],
          "onDelete": "no action",
          "onUpdate": "no action"
        }
      },
      "compositePrimaryKeys": {},
      "uniqueConstraints": {}
    },
    "roots": {
      "name": "roots",
      "schema": "",
      "columns": {
        "id": {
          "name": "id",
          "type": "serial",
          "primaryKey": true,
          "notNull": true
        },
        "root": {
          "name": "root",
          "type": "varchar(255)",
          "primaryKey": false,
          "notNull": false
        },
        "language": {
          "name": "language",
          "type": "varchar(255)",
          "primaryKey": false,
          "notNull": true
        },
        "user_id": {
          "name": "user_id",
          "type": "text",
          "primaryKey": false,
          "notNull": false
        },
        "word_id": {
          "name": "word_id",
          "type": "integer",
          "primaryKey": false,
          "notNull": true
        }
      },
      "indexes": {},
      "foreignKeys": {},
      "compositePrimaryKeys": {},
      "uniqueConstraints": {}
    },
    "saved_words": {
      "name": "saved_words",
      "schema": "",
      "columns": {
        "user_id": {
          "name": "user_id",
          "type": "text",
          "primaryKey": false,
          "notNull": true
        },
        "word_id": {
          "name": "word_id",
          "type": "integer",
          "primaryKey": false,
          "notNull": true
        },
        "createdAt": {
          "name": "createdAt",
          "type": "timestamp",
          "primaryKey": false,
          "notNull": false,
          "default": "now()"
        }
      },
      "indexes": {},
      "foreignKeys": {
        "saved_words_user_id_users_id_fk": {
          "name": "saved_words_user_id_users_id_fk",
          "tableFrom": "saved_words",
          "tableTo": "users",
          "columnsFrom": [
            "user_id"
          ],
          "columnsTo": [
            "id"
          ],
          "onDelete": "cascade",
          "onUpdate": "no action"
        },
        "saved_words_word_id_words_id_fk": {
          "name": "saved_words_word_id_words_id_fk",
          "tableFrom": "saved_words",
          "tableTo": "words",
          "columnsFrom": [
            "word_id"
          ],
          "columnsTo": [
            "id"
          ],
          "onDelete": "cascade",
          "onUpdate": "no action"
        }
      },
      "compositePrimaryKeys": {
        "saved_words_user_id_word_id_pk": {
          "name": "saved_words_user_id_word_id_pk",
          "columns": [
            "user_id",
            "word_id"
          ]
        }
      },
      "uniqueConstraints": {}
    },
    "users": {
      "name": "users",
      "schema": "",
      "columns": {
        "id": {
          "name": "id",
          "type": "text",
          "primaryKey": true,
          "notNull": true
        },
        "name": {
          "name": "name",
          "type": "text",
          "primaryKey": false,
          "notNull": false
        },
        "email": {
          "name": "email",
          "type": "text",
          "primaryKey": false,
          "notNull": true
        },
        "emailVerified": {
          "name": "emailVerified",
          "type": "timestamp",
          "primaryKey": false,
          "notNull": false
        },
        "image": {
          "name": "image",
          "type": "text",
          "primaryKey": false,
          "notNull": false
        },
        "username": {
          "name": "username",
          "type": "varchar(255)",
          "primaryKey": false,
          "notNull": false
        },
        "password": {
          "name": "password",
          "type": "varchar(510)",
          "primaryKey": false,
          "notNull": false
        },
        "role": {
          "name": "role",
          "type": "role",
          "primaryKey": false,
          "notNull": true,
          "default": "'user'"
        }
      },
      "indexes": {},
      "foreignKeys": {},
      "compositePrimaryKeys": {},
      "uniqueConstraints": {}
    },
    "word_attributes": {
      "name": "word_attributes",
      "schema": "",
      "columns": {
        "id": {
          "name": "id",
          "type": "serial",
          "primaryKey": true,
          "notNull": true
        },
        "attribute": {
          "name": "attribute",
          "type": "varchar(255)",
          "primaryKey": false,
          "notNull": true
        }
      },
      "indexes": {},
      "foreignKeys": {},
      "compositePrimaryKeys": {},
      "uniqueConstraints": {}
    },
    "words_attributes": {
      "name": "words_attributes",
      "schema": "",
      "columns": {
        "word_id": {
          "name": "word_id",
          "type": "integer",
          "primaryKey": false,
          "notNull": false
        },
        "attribute_id": {
          "name": "attribute_id",
          "type": "integer",
          "primaryKey": false,
          "notNull": false
        }
      },
      "indexes": {},
      "foreignKeys": {
        "words_attributes_word_id_words_id_fk": {
          "name": "words_attributes_word_id_words_id_fk",
          "tableFrom": "words_attributes",
          "tableTo": "words",
          "columnsFrom": [
            "word_id"
          ],
          "columnsTo": [
            "id"
          ],
          "onDelete": "cascade",
          "onUpdate": "no action"
        },
        "words_attributes_attribute_id_word_attributes_id_fk": {
          "name": "words_attributes_attribute_id_word_attributes_id_fk",
          "tableFrom": "words_attributes",
          "tableTo": "word_attributes",
          "columnsFrom": [
            "attribute_id"
          ],
          "columnsTo": [
            "id"
          ],
          "onDelete": "cascade",
          "onUpdate": "no action"
        }
      },
      "compositePrimaryKeys": {
        "words_attributes_word_id_attribute_id_pk": {
          "name": "words_attributes_word_id_attribute_id_pk",
          "columns": [
            "word_id",
            "attribute_id"
          ]
        }
      },
      "uniqueConstraints": {}
    },
    "words": {
      "name": "words",
      "schema": "",
      "columns": {
        "id": {
          "name": "id",
          "type": "serial",
          "primaryKey": true,
          "notNull": true
        },
        "name": {
          "name": "name",
          "type": "varchar(255)",
          "primaryKey": false,
          "notNull": true
        },
        "phonetic": {
          "name": "phonetic",
          "type": "varchar(255)",
          "primaryKey": false,
          "notNull": false
        },
        "root_id": {
          "name": "root_id",
          "type": "integer",
          "primaryKey": false,
          "notNull": false
        },
        "created_at": {
          "name": "created_at",
          "type": "date",
          "primaryKey": false,
          "notNull": false,
          "default": "now()"
        },
        "updated_at": {
          "name": "updated_at",
          "type": "date",
          "primaryKey": false,
          "notNull": false
        },
        "related_phrases": {
          "name": "related_phrases",
          "type": "text[]",
          "primaryKey": false,
          "notNull": false
        },
        "prefix": {
          "name": "prefix",
          "type": "varchar(255)",
          "primaryKey": false,
          "notNull": false
        },
        "suffix": {
          "name": "suffix",
          "type": "varchar(255)",
          "primaryKey": false,
          "notNull": false
        }
      },
      "indexes": {},
      "foreignKeys": {},
      "compositePrimaryKeys": {},
      "uniqueConstraints": {}
    }
  },
  "enums": {
    "partOfSpeech": {
      "name": "partOfSpeech",
      "values": {
        "isim": "isim",
        "fiil": "fiil",
        "sıfat": "sıfat",
        "zarf": "zarf",
        "zamir": "zamir",
        "ünlem": "ünlem",
        "edat": "edat",
        "bağlaç": "bağlaç"
      }
    },
    "action": {
      "name": "action",
      "values": {
        "create": "create",
        "update": "update",
        "delete": "delete"
      }
    },
    "entity_type": {
      "name": "entity_type",
      "values": {
        "words": "words",
        "meanings": "meanings",
        "roots": "roots",
        "related_words": "related_words",
        "part_of_speechs": "part_of_speechs",
        "examples": "examples",
        "authors": "authors",
        "word_attributes": "word_attributes",
        "meaning_attributes": "meaning_attributes"
      }
    },
    "status": {
      "name": "status",
      "values": {
        "pending": "pending",
        "approved": "approved",
        "rejected": "rejected"
      }
    },
    "role": {
      "name": "role",
      "values": {
        "user": "user",
        "moderator": "moderator",
        "admin": "admin"
      }
    }
  },
  "schemas": {},
  "_meta": {
    "schemas": {},
    "tables": {
      "\"user\"": "\"users\""
    },
    "columns": {}
  }
}